ntc_templates/__init__.py
ntc_templates/parse.py
ntc_templates/templates/alcatel_aos_show_vlan.textfsm
ntc_templates/templates/alcatel_sros_oam_mac-ping.textfsm
ntc_templates/templates/alcatel_sros_show_lag.textfsm
ntc_templates/templates/alcatel_sros_show_port.textfsm
ntc_templates/templates/alcatel_sros_show_router_bgp_routes_vpn-ipv4.textfsm
ntc_templates/templates/alcatel_sros_show_router_bgp_summary_family.textfsm
ntc_templates/templates/alcatel_sros_show_router_interface.textfsm
ntc_templates/templates/alcatel_sros_show_router_isis_adjacency.textfsm
ntc_templates/templates/alcatel_sros_show_router_isis_interface.textfsm
ntc_templates/templates/alcatel_sros_show_router_ldp_interface.textfsm
ntc_templates/templates/alcatel_sros_show_router_mpls_interface.textfsm
ntc_templates/templates/alcatel_sros_show_router_mpls_lsp.textfsm
ntc_templates/templates/alcatel_sros_show_router_ospf_interface.textfsm
ntc_templates/templates/alcatel_sros_show_router_pim_interface.textfsm
ntc_templates/templates/alcatel_sros_show_router_rsvp_interface.textfsm
ntc_templates/templates/alcatel_sros_show_service_id_base.textfsm
ntc_templates/templates/alcatel_sros_show_service_sap-using.textfsm
ntc_templates/templates/alcatel_sros_show_service_sdp-using.textfsm
ntc_templates/templates/alcatel_sros_show_service_sdp.textfsm
ntc_templates/templates/alcatel_sros_show_system_cpu.textfsm
ntc_templates/templates/arista_eos_bash_df_-h.textfsm
ntc_templates/templates/arista_eos_dir_flash.textfsm
ntc_templates/templates/arista_eos_show_boot-config.textfsm
ntc_templates/templates/arista_eos_show_clock.textfsm
ntc_templates/templates/arista_eos_show_environment_cooling.textfsm
ntc_templates/templates/arista_eos_show_environment_temperature.textfsm
ntc_templates/templates/arista_eos_show_hostname.textfsm
ntc_templates/templates/arista_eos_show_interfaces.textfsm
ntc_templates/templates/arista_eos_show_interfaces_description.textfsm
ntc_templates/templates/arista_eos_show_interfaces_status.textfsm
ntc_templates_bsh-2.3.1.dist-info/LICENSE
ntc_templates_bsh-2.3.1.dist-info/WHEEL
ntc_templates_bsh-2.3.1.dist-info/METADATA
ntc_templates_bsh-2.3.1.dist-info/RECORD
