Metadata-Version: 2.1
Name: ntc-templates-bsh
Version: 2.3.1
Summary: TextFSM Templates for Network Devices, and Python wrapper for TextFSM's CliTable.
Home-page: https://github.com/bsh-developers/ntc-templates-bsh
License: Apache-2.0
Author: Network to Code
Author-email: info@networktocode.com
Requires-Python: >=3.6,<4.0
Classifier: License :: OSI Approved :: Apache Software License
Classifier: Programming Language :: Python :: 3
Classifier: Programming Language :: Python :: 3.6
Classifier: Programming Language :: Python :: 3.7
Classifier: Programming Language :: Python :: 3.8
Classifier: Programming Language :: Python :: 3.9
Provides-Extra: test
Requires-Dist: textfsm (>=1.1.0,<2.0.0)
Project-URL: Repository, https://github.com/bsh-developers/ntc-templates-bsh
